examples/load_photometry_data.ipynb
examples/process_photometry_data.ipynb
gui/rawdata_visualizer.py
iblphotometry/__init__.py
iblphotometry/behavior.py
iblphotometry/io.py
iblphotometry/loaders.py
iblphotometry/metrics.py
iblphotometry/neurophotometrics.py
iblphotometry/pipelines.py
iblphotometry/plots.py
iblphotometry/preprocessing.py
iblphotometry/processing.py
iblphotometry/qc.py
iblphotometry/synthetic.py
iblphotometry_tests/__init__.py
iblphotometry_tests/base_tests.py
iblphotometry_tests/test_loaders.py
iblphotometry_tests/test_metrics.py
iblphotometry_tests/test_pipelines.py
iblphotometry_tests/test_plots.py
iblphotometry_tests/test_processing.py
iblphotometry_tests/data/_ibl_trials.table.pqt
iblphotometry_tests/data/raw_photometry.csv
iblphotometry_tests/data/raw_photometry.pqt
iblphotometry_tests/data/77a6741c-81cc-475f-9454-a9b997be02a4/Region3G/raw_photometry.pqt
iblphotometry_tests/data/cortexlab/Subjects/CQ002/2024-11-05/001/_ibl_experiment.description.yaml
iblphotometry_tests/data/cortexlab/Subjects/CQ002/2024-11-05/001/alf/photometry/photometry.signal.pqt
iblphotometry_tests/data/cortexlab/Subjects/CQ002/2024-11-05/001/alf/photometry/photometryROI.locations.pqt
iblphotometry_tests/data/cortexlab/Subjects/CQ002/2024-11-05/001/alf/task_00/_ibl_trials.table.pqt
iblphotometry_tests/data/cortexlab/Subjects/CQ002/2024-11-05/001/raw_photometry_data/_neurophotometrics_fpData.raw.pqt
iblphotometry_tests/data/wittenlab/Subjects/fip_40/2023-05-18/001/alf/_ibl_trials.table.pqt
iblphotometry_tests/data/wittenlab/Subjects/fip_40/2023-05-18/001/alf/photometry/photometry.signal.pqt
iblphotometry_tests/data/wittenlab/Subjects/fip_40/2023-05-18/001/alf/photometry/photometryROI.locations.pqt
iblphotometry_tests/data/wittenlab/Subjects/fip_40/2023-05-18/001/raw_photometry_data/_neurophotometrics_fpData.raw.pqt
ibl_photometry-1.0.0.dist-info/LICENSE
ibl_photometry-1.0.0.dist-info/METADATA
ibl_photometry-1.0.0.dist-info/WHEEL
ibl_photometry-1.0.0.dist-info/entry_points.txt
ibl_photometry-1.0.0.dist-info/top_level.txt
ibl_photometry-1.0.0.dist-info/RECORD
