Metadata-Version: 2.1
Name: ibl-photometry
Version: 1.0.0
Summary: IBL photometry module
Author-email: IBL staff <info@internationalbrainlab.org>
License: MIT License
Project-URL: Homepage, https://github.com/int-brain-lab/iblphotometry
Classifier: Programming Language :: Python :: 3
Classifier: License :: OSI Approved :: MIT License
Classifier: Operating System :: OS Independent
Requires-Python: >=3.10
License-File: LICENSE
Requires-Dist: ibllib
Requires-Dist: numpy
Requires-Dist: matplotlib
Requires-Dist: pytest
Requires-Dist: scipy
Requires-Dist: pandera
Requires-Dist: pywavelets
